LICENSE
README.md
setup.py
feature_engineer_hurlok/__init__.py
feature_engineer_hurlok/feature_selection.py
feature_engineer_hurlok.egg-info/PKG-INFO
feature_engineer_hurlok.egg-info/SOURCES.txt
feature_engineer_hurlok.egg-info/dependency_links.txt
feature_engineer_hurlok.egg-info/requires.txt
feature_engineer_hurlok.egg-info/top_level.txt