Metadata-Version: 2.1
Name: feature-engineer-hurlok
Version: 0.0.10
Summary: Exemplo de pacote PyPI
Home-page: https://github.com/illiamw/PackagePiP
Author: William Ferreira
Author-email: williambox37@gmail.com
License: MIT License
Keywords: Pacote
License-File: LICENSE
